{
    "display_name": "Unknown_TIVO",
    "ir": {
        "commands": [
            {
                "address": "0",
                "name": "TIVO"
            },
            {
                "address": "11",
                "name": "KEY_TV"
            },
            {
                "address": "14",
                "name": "KEY_UP"
            },
            {
                "address": "15",
                "name": "KEY_RIGHT"
            },
            {
                "address": "16",
                "name": "KEY_DOWN"
            },
            {
                "address": "17",
                "name": "KEY_LEFT"
            },
            {
                "address": "18",
                "name": "THUMBSDOWN"
            },
            {
                "address": "19",
                "name": "KEY_SELECT"
            },
            {
                "address": "1A",
                "name": "THUMBSUP"
            },
            {
                "address": "1E",
                "name": "KEY_CHANNELUP"
            },
            {
                "address": "1F",
                "name": "KEY_CHANNELDOWN"
            },
            {
                "address": "20",
                "name": "KEY_RECORD"
            },
            {
                "address": "21",
                "name": "KEY_PLAY"
            },
            {
                "address": "22",
                "name": "REV"
            },
            {
                "address": "23",
                "name": "KEY_PAUSE"
            },
            {
                "address": "24",
                "name": "KEY_FORWARD"
            },
            {
                "address": "25",
                "name": "KEY_SLOW"
            },
            {
                "address": "26",
                "name": "KEY_AGAIN"
            },
            {
                "address": "27",
                "name": "JUMPTOEND"
            },
            {
                "address": "28",
                "name": "KEY_1"
            },
            {
                "address": "29",
                "name": "KEY_2"
            },
            {
                "address": "2A",
                "name": "KEY_3"
            },
            {
                "address": "2B",
                "name": "KEY_4"
            },
            {
                "address": "2C",
                "name": "KEY_5"
            },
            {
                "address": "2D",
                "name": "KEY_6"
            },
            {
                "address": "2E",
                "name": "KEY_7"
            },
            {
                "address": "2F",
                "name": "KEY_8"
            },
            {
                "address": "30",
                "name": "KEY_9"
            },
            {
                "address": "31",
                "name": "KEY_0"
            },
            {
                "address": "32",
                "name": "KEY_CLEAR"
            },
            {
                "address": "33",
                "name": "KEY_ENTER"
            }
        ],
        "device_address": "850000",
        "protocol": "TIVO UNIT=0"
    },
    "manufacturer": "Philips",
    "model": "",
    "name": "Philips Unknown_TIVO",
    "target": "Unknown_TIVO"
}
