{
    "display_name": "Unknown_mivar",
    "ir": {
        "commands": [
            {
                "address": "2",
                "name": "KEY_2"
            },
            {
                "address": "3",
                "name": "KEY_3"
            },
            {
                "address": "4",
                "name": "KEY_1"
            },
            {
                "address": "5",
                "name": "KEY_4"
            },
            {
                "address": "6",
                "name": "KEY_5"
            },
            {
                "address": "A",
                "name": "KEY_7"
            },
            {
                "address": "B",
                "name": "KEY_8"
            },
            {
                "address": "C",
                "name": "KEY_6"
            },
            {
                "address": "D",
                "name": "KEY_9"
            },
            {
                "address": "E",
                "name": "KEY_0"
            },
            {
                "address": "12",
                "name": "KEY_VOLUMEUP"
            },
            {
                "address": "14",
                "name": "KEY_CHANNELUP"
            },
            {
                "address": "15",
                "name": "Lum+"
            },
            {
                "address": "16",
                "name": "Col+"
            },
            {
                "address": "1A",
                "name": "KEY_VOLUMEDOWN"
            },
            {
                "address": "1C",
                "name": "KEY_CHANNELDOWN"
            },
            {
                "address": "1D",
                "name": "Lum-"
            },
            {
                "address": "1E",
                "name": "Col-"
            },
            {
                "address": "22",
                "name": "V-M"
            },
            {
                "address": "24",
                "name": "P/C"
            },
            {
                "address": "25",
                "name": "Muto"
            },
            {
                "address": "26",
                "name": "L1-L2"
            },
            {
                "address": "2A",
                "name": "Canc"
            },
            {
                "address": "2B",
                "name": "TV-TVD"
            },
            {
                "address": "2C",
                "name": "KEY_STOP"
            },
            {
                "address": "2D",
                "name": "All"
            },
            {
                "address": "2E",
                "name": "Riv"
            },
            {
                "address": "33",
                "name": "spento"
            },
            {
                "address": "34",
                "name": "Ora"
            },
            {
                "address": "36",
                "name": "AV"
            }
        ],
        "device_address": "-80000000",
        "protocol": "RECS80"
    },
    "manufacturer": "mivar",
    "model": "",
    "name": "Unknown_mivar",
    "target": "Unknown_mivar"
}
