{
    "display_name": "Unknown_RC40",
    "ir": {
        "commands": [
            {
                "address": "0",
                "name": "STANDBY_ON-OFF"
            },
            {
                "address": "4",
                "name": "KEY_1"
            },
            {
                "address": "5",
                "name": "KEY_2"
            },
            {
                "address": "6",
                "name": "KEY_3"
            },
            {
                "address": "7",
                "name": "KEY_4"
            },
            {
                "address": "C",
                "name": "KEY_5"
            },
            {
                "address": "D",
                "name": "KEY_6"
            },
            {
                "address": "E",
                "name": "KEY_7"
            },
            {
                "address": "F",
                "name": "KEY_8"
            },
            {
                "address": "10",
                "name": "KEY_STOP"
            },
            {
                "address": "11",
                "name": "KEY_PAUSE"
            },
            {
                "address": "12",
                "name": "KEY_REWIND"
            },
            {
                "address": "13",
                "name": "KEY_FASTFORWARD"
            },
            {
                "address": "14",
                "name": "KEY_PLAY"
            },
            {
                "address": "1C",
                "name": "KEY_9"
            },
            {
                "address": "1D",
                "name": "KEY_0"
            }
        ],
        "device_address": "-80000000",
        "protocol": "NEC"
    },
    "manufacturer": "ITT",
    "model": "",
    "name": "ITT Unknown_RC40",
    "target": "Unknown_RC40"
}
