{
    "display_name": "Toshiba Unknown_TSR-101R",
    "ir": {
        "commands": [
            {
                "address": "81",
                "name": "KEY_1"
            },
            {
                "address": "82",
                "name": "KEY_2"
            },
            {
                "address": "83",
                "name": "KEY_3"
            },
            {
                "address": "84",
                "name": "KEY_4"
            },
            {
                "address": "85",
                "name": "KEY_5"
            },
            {
                "address": "86",
                "name": "KEY_6"
            },
            {
                "address": "87",
                "name": "KEY_7"
            },
            {
                "address": "88",
                "name": "KEY_8"
            },
            {
                "address": "89",
                "name": "KEY_9"
            },
            {
                "address": "8a",
                "name": "KEY_0"
            },
            {
                "address": "8b",
                "name": "KEY_ENTER"
            },
            {
                "address": "8e",
                "name": "antenna"
            },
            {
                "address": "92",
                "name": "KEY_POWER"
            },
            {
                "address": "94",
                "name": "KEY_INFO"
            },
            {
                "address": "95",
                "name": "surf"
            },
            {
                "address": "9a",
                "name": "dss"
            },
            {
                "address": "9b",
                "name": "KEY_CHANNELUP"
            },
            {
                "address": "9c",
                "name": "alternate"
            },
            {
                "address": "9f",
                "name": "KEY_CHANNELDOWN"
            },
            {
                "address": "c0",
                "name": "timer"
            },
            {
                "address": "c8",
                "name": "KEY_UP"
            },
            {
                "address": "c9",
                "name": "KEY_DOWN"
            },
            {
                "address": "ca",
                "name": "KEY_RIGHT"
            },
            {
                "address": "cb",
                "name": "KEY_LEFT"
            },
            {
                "address": "cc",
                "name": "display"
            },
            {
                "address": "d1",
                "name": "KEY_EXIT"
            },
            {
                "address": "d4",
                "name": "KEY_MENU"
            },
            {
                "address": "d7",
                "name": "KEY_FAVORITES"
            },
            {
                "address": "db",
                "name": "KEY_RECORD"
            }
        ],
        "device_address": "10000000",
        "protocol": "NEC"
    },
    "manufacturer": "Toshiba",
    "model": "",
    "name": "",
    "target": "Unknown_TSR-101R"
}
