{
    "display_name": "Amplifier",
    "ir": {
        "commands": [
            {
                "address": "A",
                "name": "display"
            },
            {
                "address": "C",
                "name": "Power"
            },
            {
                "address": "10",
                "name": "Volume Up"
            },
            {
                "address": "11",
                "name": "Volume Down"
            },
            {
                "address": "1E",
                "name": "input up"
            },
            {
                "address": "1F",
                "name": "input down"
            }
        ],
        "device_address": "0",
        "protocol": "RC5"
    },
    "manufacturer": "Primare",
    "model": "",
    "name": "Primare Amplifier",
    "target": "Amplifier"
}
