{
    "display_name": "Sirius Unknown_SBKB-3201KR",
    "ir": {
        "commands": [
            {
                "address": "a",
                "name": "KEY_CHANNELUP"
            },
            {
                "address": "b",
                "name": "KEY_CHANNELDOWN"
            },
            {
                "address": "c",
                "name": "cat-"
            },
            {
                "address": "d",
                "name": "cat+"
            },
            {
                "address": "e",
                "name": "KEY_SELECT"
            },
            {
                "address": "f",
                "name": "KEY_POWER"
            },
            {
                "address": "10",
                "name": "KEY_0"
            },
            {
                "address": "11",
                "name": "KEY_1"
            },
            {
                "address": "12",
                "name": "KEY_2"
            },
            {
                "address": "13",
                "name": "KEY_3"
            },
            {
                "address": "14",
                "name": "KEY_4"
            },
            {
                "address": "15",
                "name": "KEY_5"
            },
            {
                "address": "16",
                "name": "KEY_6"
            },
            {
                "address": "17",
                "name": "KEY_7"
            },
            {
                "address": "18",
                "name": "KEY_8"
            },
            {
                "address": "19",
                "name": "KEY_9"
            },
            {
                "address": "1a",
                "name": "KEY_PREVIOUS"
            },
            {
                "address": "1c",
                "name": "direct"
            },
            {
                "address": "1d",
                "name": "KEY_MUTE"
            },
            {
                "address": "1e",
                "name": "KEY_MENU"
            },
            {
                "address": "1f",
                "name": "band"
            },
            {
                "address": "21",
                "name": "memo"
            },
            {
                "address": "22",
                "name": "disp"
            }
        ],
        "device_address": "0",
        "protocol": "NEC"
    },
    "manufacturer": "Sirius",
    "model": "",
    "name": "",
    "target": "Unknown_SBKB-3201KR"
}
