{
    "display_name": "Unknown_SAT",
    "ir": {
        "commands": [
            {
                "address": "0",
                "name": "KEY_0"
            },
            {
                "address": "1",
                "name": "KEY_1"
            },
            {
                "address": "2",
                "name": "KEY_2"
            },
            {
                "address": "3",
                "name": "KEY_3"
            },
            {
                "address": "4",
                "name": "KEY_4"
            },
            {
                "address": "5",
                "name": "KEY_5"
            },
            {
                "address": "6",
                "name": "KEY_6"
            },
            {
                "address": "7",
                "name": "KEY_7"
            },
            {
                "address": "8",
                "name": "KEY_8"
            },
            {
                "address": "9",
                "name": "KEY_9"
            },
            {
                "address": "A",
                "name": "KEY_POWER"
            },
            {
                "address": "B",
                "name": "KEY_MUTE"
            },
            {
                "address": "C",
                "name": "KEY_EPG"
            },
            {
                "address": "D",
                "name": "KEY_VOLUMEDOWN"
            },
            {
                "address": "E",
                "name": "KEY_VOLUMEUP"
            },
            {
                "address": "F",
                "name": "TV/RADIO"
            },
            {
                "address": "10",
                "name": "KEY_FAVORITES"
            },
            {
                "address": "12",
                "name": "KEY_CHANNELUP"
            },
            {
                "address": "13",
                "name": "KEY_CHANNELDOWN"
            },
            {
                "address": "16",
                "name": "KEY_AUDIO"
            },
            {
                "address": "17",
                "name": "KEY_I"
            },
            {
                "address": "18",
                "name": "KEY_EXIT"
            },
            {
                "address": "19",
                "name": "KEY_LAST"
            },
            {
                "address": "1A",
                "name": "KEY_TEXT"
            },
            {
                "address": "1B",
                "name": "KEY_OK"
            },
            {
                "address": "1C",
                "name": "KEY_MENU"
            },
            {
                "address": "1D",
                "name": "ALT"
            },
            {
                "address": "1E",
                "name": "KEY_CHANNELDOWN"
            },
            {
                "address": "1F",
                "name": "KEY_CHANNELUP"
            }
        ],
        "device_address": "-80000000",
        "protocol": "NEC"
    },
    "manufacturer": "Samsung",
    "model": "",
    "name": "Samsung Unknown_SAT",
    "target": "Unknown_SAT"
}
