{
    "display_name": "Palcom Unknown_DSL-6",
    "ir": {
        "commands": [
            {
                "address": "80",
                "name": "KEY_EPG"
            },
            {
                "address": "81",
                "name": "KEY_BLUE"
            },
            {
                "address": "82",
                "name": "KEY_MENU"
            },
            {
                "address": "83",
                "name": "KEY_PAGEDOWN"
            },
            {
                "address": "84",
                "name": "KEY_CHANNELDOWN"
            },
            {
                "address": "85",
                "name": "KEY_GREEN"
            },
            {
                "address": "86",
                "name": "KEY_YELLOW"
            },
            {
                "address": "87",
                "name": "KEY_PAGEUP"
            },
            {
                "address": "88",
                "name": "KEY_OK"
            },
            {
                "address": "89",
                "name": "KEY_VOLUMEDOWN"
            },
            {
                "address": "8a",
                "name": "KEY_VOLUMEUP"
            },
            {
                "address": "8b",
                "name": "KEY_RED"
            },
            {
                "address": "8c",
                "name": "KEY_CHANNELUP"
            },
            {
                "address": "8d",
                "name": "KEY_EXIT"
            },
            {
                "address": "8e",
                "name": "Freeze"
            },
            {
                "address": "8f",
                "name": "Speaker_on_off"
            },
            {
                "address": "90",
                "name": "KEY_0"
            },
            {
                "address": "91",
                "name": "KEY_9"
            },
            {
                "address": "92",
                "name": "KEY_TEXT"
            },
            {
                "address": "93",
                "name": "browse"
            },
            {
                "address": "94",
                "name": "KEY_6"
            },
            {
                "address": "95",
                "name": "KEY_5"
            },
            {
                "address": "96",
                "name": "KEY_7"
            },
            {
                "address": "97",
                "name": "KEY_8"
            },
            {
                "address": "98",
                "name": "KEY_2"
            },
            {
                "address": "99",
                "name": "KEY_1"
            },
            {
                "address": "9a",
                "name": "KEY_3"
            },
            {
                "address": "9b",
                "name": "KEY_4"
            },
            {
                "address": "9c",
                "name": "TV/Rad"
            },
            {
                "address": "9d",
                "name": "KEY_AUDIO"
            },
            {
                "address": "9e",
                "name": "KEY_TV"
            },
            {
                "address": "9f",
                "name": "KEY_POWER"
            },
            {
                "address": "d4",
                "name": "KEY_INFO"
            },
            {
                "address": "d8",
                "name": "Alt"
            },
            {
                "address": "dc",
                "name": "KEY_SUBTITLE"
            }
        ],
        "device_address": "0",
        "protocol": "NEC"
    },
    "manufacturer": "Palcom",
    "model": "",
    "name": "",
    "target": "Unknown_DSL-6"
}
