{
    "display_name": "Unknown_Kitty",
    "ir": {
        "commands": [
            {
                "address": "80",
                "name": "KEY_5"
            },
            {
                "address": "81",
                "name": "KEY_1"
            },
            {
                "address": "82",
                "name": "KEY_4"
            },
            {
                "address": "83",
                "name": "KEY_2"
            },
            {
                "address": "84",
                "name": "title-return"
            },
            {
                "address": "86",
                "name": "KEY_SUBTITLE"
            },
            {
                "address": "88",
                "name": "rev"
            },
            {
                "address": "8C",
                "name": "KEY_0"
            },
            {
                "address": "8D",
                "name": "KEY_7"
            },
            {
                "address": "8F",
                "name": "KEY_8"
            },
            {
                "address": "90",
                "name": "KEY_LEFT"
            },
            {
                "address": "91",
                "name": "display"
            },
            {
                "address": "92",
                "name": "KEY_SEARCH"
            },
            {
                "address": "93",
                "name": "enter-play"
            },
            {
                "address": "94",
                "name": "repeatAB"
            },
            {
                "address": "96",
                "name": "KEY_MUTE"
            },
            {
                "address": "C0",
                "name": "KEY_6"
            },
            {
                "address": "C1",
                "name": "KEY_3"
            },
            {
                "address": "C2",
                "name": "KEY_ANGLE"
            },
            {
                "address": "C4",
                "name": "KEY_AUDIO"
            },
            {
                "address": "C5",
                "name": "KEY_POWER"
            },
            {
                "address": "C6",
                "name": "KEY_MENU"
            },
            {
                "address": "C7",
                "name": "KEY_OPEN"
            },
            {
                "address": "C8",
                "name": "KEY_FORWARD"
            },
            {
                "address": "C9",
                "name": "KEY_STOP"
            },
            {
                "address": "CC",
                "name": "KEY_CLEAR"
            },
            {
                "address": "CD",
                "name": "KEY_9"
            },
            {
                "address": "CE",
                "name": "KEY_ZOOM"
            },
            {
                "address": "D0",
                "name": "KEY_DOWN"
            },
            {
                "address": "D1",
                "name": "KEY_UP"
            },
            {
                "address": "D2",
                "name": "KEY_RIGHT"
            },
            {
                "address": "D3",
                "name": "KEY_SETUP"
            },
            {
                "address": "D7",
                "name": "KEY_PAUSE"
            }
        ],
        "device_address": "0",
        "protocol": "NEC"
    },
    "manufacturer": "Hello Kitty",
    "model": "",
    "name": "Hello Kitty Unknown_Kitty",
    "target": "Unknown_Kitty"
}
