{
    "display_name": "TV",
    "ir": {
        "commands": [
            {
                "address": "0",
                "name": "1"
            },
            {
                "address": "0",
                "name": "TV 1"
            },
            {
                "address": "1",
                "name": "9"
            },
            {
                "address": "1",
                "name": "TV 9"
            },
            {
                "address": "2",
                "name": "POWER"
            },
            {
                "address": "2",
                "name": "TV POWER"
            },
            {
                "address": "3",
                "name": "ST/SAP/MONO"
            },
            {
                "address": "4",
                "name": "COLOR +"
            },
            {
                "address": "5",
                "name": "EXTERNAL 1"
            },
            {
                "address": "7",
                "name": "CANCEL"
            },
            {
                "address": "7",
                "name": "TV CANCEL"
            },
            {
                "address": "7",
                "name": "TV"
            },
            {
                "address": "8",
                "name": "2"
            },
            {
                "address": "8",
                "name": "TV 2"
            },
            {
                "address": "9",
                "name": "0"
            },
            {
                "address": "9",
                "name": "TV 0"
            },
            {
                "address": "A",
                "name": "CHANNEL +"
            },
            {
                "address": "A",
                "name": "CHANNEL UP"
            },
            {
                "address": "A",
                "name": "SCAN ^ (CH ^)"
            },
            {
                "address": "A",
                "name": "TV CHANNEL ^"
            },
            {
                "address": "A",
                "name": "SCAN ^(CH ^)"
            },
            {
                "address": "A",
                "name": "CHANNEL ^"
            },
            {
                "address": "B",
                "name": "RESET"
            },
            {
                "address": "C",
                "name": "COLOR -"
            },
            {
                "address": "D",
                "name": "EXTERNAL 2"
            },
            {
                "address": "F",
                "name": "QUICK VIEW"
            },
            {
                "address": "F",
                "name": "Q/V"
            },
            {
                "address": "F",
                "name": "QV"
            },
            {
                "address": "F",
                "name": "TV QV"
            },
            {
                "address": "F",
                "name": "Q.V."
            },
            {
                "address": "F",
                "name": "Q / V"
            },
            {
                "address": "F",
                "name": "RCL"
            },
            {
                "address": "10",
                "name": "3"
            },
            {
                "address": "10",
                "name": "TV 3"
            },
            {
                "address": "12",
                "name": "CHANNEL -"
            },
            {
                "address": "12",
                "name": "CHANNEL DOWN"
            },
            {
                "address": "12",
                "name": "SCAN V (CH V)"
            },
            {
                "address": "12",
                "name": "TV CHANNEL V"
            },
            {
                "address": "12",
                "name": "SCAN V(CH V)"
            },
            {
                "address": "12",
                "name": "CHANNEL V"
            },
            {
                "address": "13",
                "name": "EXP"
            },
            {
                "address": "13",
                "name": "AUDIO EXPANSION"
            },
            {
                "address": "17",
                "name": "OFF-T"
            },
            {
                "address": "17",
                "name": "TIMER"
            },
            {
                "address": "17",
                "name": "OFF-T/OTR"
            },
            {
                "address": "17",
                "name": "TV SLEEP"
            },
            {
                "address": "17",
                "name": "SLEEP"
            },
            {
                "address": "18",
                "name": "4"
            },
            {
                "address": "18",
                "name": "TV 4"
            },
            {
                "address": "1A",
                "name": "INPUT -"
            },
            {
                "address": "1A",
                "name": "ANT A/B"
            },
            {
                "address": "1A",
                "name": "INPUT V"
            },
            {
                "address": "1A",
                "name": "ANTENNA"
            },
            {
                "address": "1B",
                "name": "DISPLAY"
            },
            {
                "address": "1B",
                "name": "DISP"
            },
            {
                "address": "1B",
                "name": "TV INFO"
            },
            {
                "address": "1B",
                "name": "INFO"
            },
            {
                "address": "1B",
                "name": "DISPLAY RECALL"
            },
            {
                "address": "1F",
                "name": "CHANNEL LOCK"
            },
            {
                "address": "20",
                "name": "5"
            },
            {
                "address": "20",
                "name": "TV 5"
            },
            {
                "address": "22",
                "name": "VOLUME +"
            },
            {
                "address": "22",
                "name": "VOLUME UP"
            },
            {
                "address": "22",
                "name": "VOL ^"
            },
            {
                "address": "22",
                "name": "VOLUME ^"
            },
            {
                "address": "23",
                "name": "CONTRAST +"
            },
            {
                "address": "28",
                "name": "6"
            },
            {
                "address": "28",
                "name": "TV 6"
            },
            {
                "address": "2A",
                "name": "VOLUME -"
            },
            {
                "address": "2A",
                "name": "VOLUME DOWN"
            },
            {
                "address": "2A",
                "name": "VOL V"
            },
            {
                "address": "2A",
                "name": "VOLUME V"
            },
            {
                "address": "2B",
                "name": "CONTRAST -"
            },
            {
                "address": "2F",
                "name": "MONO"
            },
            {
                "address": "30",
                "name": "7"
            },
            {
                "address": "30",
                "name": "TV 7"
            },
            {
                "address": "31",
                "name": "INPUT; VGA"
            },
            {
                "address": "32",
                "name": "MUTE"
            },
            {
                "address": "32",
                "name": "MUTING"
            },
            {
                "address": "33",
                "name": "AV MEMORY"
            },
            {
                "address": "33",
                "name": "TINT +"
            },
            {
                "address": "35",
                "name": "ENTER"
            },
            {
                "address": "35",
                "name": "ENTER/EXCH"
            },
            {
                "address": "35",
                "name": "TV ENTER"
            },
            {
                "address": "35",
                "name": "EXCH"
            },
            {
                "address": "36",
                "name": "SUB"
            },
            {
                "address": "37",
                "name": "SAP"
            },
            {
                "address": "38",
                "name": "8"
            },
            {
                "address": "38",
                "name": "TV 8"
            },
            {
                "address": "39",
                "name": "ANT A/B"
            },
            {
                "address": "3A",
                "name": "INPUT +"
            },
            {
                "address": "3A",
                "name": "TV/EXT1/2"
            },
            {
                "address": "3A",
                "name": "INPUT ^"
            },
            {
                "address": "3A",
                "name": "TV INPUT"
            },
            {
                "address": "3A",
                "name": "INPUT"
            },
            {
                "address": "3A",
                "name": "DEVICE"
            },
            {
                "address": "3A",
                "name": "INPUT SOURCE"
            },
            {
                "address": "3B",
                "name": "TINT -"
            },
            {
                "address": "3E",
                "name": "FORMAT"
            },
            {
                "address": "3F",
                "name": "STEREO"
            },
            {
                "address": "40",
                "name": "VIDEO ^"
            },
            {
                "address": "40",
                "name": "VIDEO"
            },
            {
                "address": "40",
                "name": "TV VIDEO"
            },
            {
                "address": "41",
                "name": "CURSOR UP"
            },
            {
                "address": "41",
                "name": "ADJUST ^"
            },
            {
                "address": "41",
                "name": "UP"
            },
            {
                "address": "41",
                "name": "TV ADJUST ^"
            },
            {
                "address": "41",
                "name": "ADJUST"
            },
            {
                "address": "41",
                "name": "ARROW UP"
            },
            {
                "address": "42",
                "name": "ON"
            },
            {
                "address": "42",
                "name": "POWER ON"
            },
            {
                "address": "43",
                "name": "FUNCTION"
            },
            {
                "address": "45",
                "name": "FUNCTION <"
            },
            {
                "address": "48",
                "name": "VIDEO V"
            },
            {
                "address": "49",
                "name": "CURSOR DOWN"
            },
            {
                "address": "49",
                "name": "ADJUST V"
            },
            {
                "address": "49",
                "name": "DOWN"
            },
            {
                "address": "49",
                "name": "TV EXCH V"
            },
            {
                "address": "49",
                "name": "TV ADJUST V"
            },
            {
                "address": "49",
                "name": "ARROW DOWN"
            },
            {
                "address": "4A",
                "name": "OFF"
            },
            {
                "address": "4A",
                "name": "POWER OFF"
            },
            {
                "address": "4C",
                "name": "ANT B"
            },
            {
                "address": "4C",
                "name": "INPUT: ANTENNA B"
            },
            {
                "address": "4E",
                "name": "SQV"
            },
            {
                "address": "4E",
                "name": "TV SQV"
            },
            {
                "address": "50",
                "name": "AUDIO ^"
            },
            {
                "address": "50",
                "name": "AUDIO"
            },
            {
                "address": "50",
                "name": "TV AUDIO"
            },
            {
                "address": "52",
                "name": "MENU"
            },
            {
                "address": "52",
                "name": "TV MENU"
            },
            {
                "address": "52",
                "name": "MUNU"
            },
            {
                "address": "54",
                "name": "UNKNOWN #2"
            },
            {
                "address": "58",
                "name": "AUDIO V"
            },
            {
                "address": "59",
                "name": "INPUT; VIDEO 5"
            },
            {
                "address": "5A",
                "name": "ANT A"
            },
            {
                "address": "5A",
                "name": "INPUT: ANTENNA A"
            },
            {
                "address": "5C",
                "name": "FUNCTION >"
            },
            {
                "address": "5C",
                "name": "UNKNOWN #1"
            },
            {
                "address": "5F",
                "name": "PIP SOURCE"
            },
            {
                "address": "5F",
                "name": "TV SOURCE"
            },
            {
                "address": "5F",
                "name": "SOURCE"
            },
            {
                "address": "5F",
                "name": "PIP INPUT"
            },
            {
                "address": "61",
                "name": "INPUT; COMP 2"
            },
            {
                "address": "62",
                "name": "INPUT 1"
            },
            {
                "address": "62",
                "name": "INPUT: VIDEO 1"
            },
            {
                "address": "63",
                "name": "TV GUIDE"
            },
            {
                "address": "63",
                "name": "GUIDE"
            },
            {
                "address": "65",
                "name": "CURSOR LEFT"
            },
            {
                "address": "65",
                "name": "LEFT"
            },
            {
                "address": "65",
                "name": "TV <"
            },
            {
                "address": "65",
                "name": "TV ADJUST <"
            },
            {
                "address": "65",
                "name": "ARROW LEFT"
            },
            {
                "address": "67",
                "name": "FREEZE (PAUSE)"
            },
            {
                "address": "69",
                "name": "INPUT; COMP 1"
            },
            {
                "address": "6A",
                "name": "INPUT 2"
            },
            {
                "address": "6A",
                "name": "INPUT: VIDEO 2"
            },
            {
                "address": "6D",
                "name": "CURSOR RIGHT"
            },
            {
                "address": "6D",
                "name": "RIGHT"
            },
            {
                "address": "6D",
                "name": "TV >"
            },
            {
                "address": "6D",
                "name": "TV ADJUST >"
            },
            {
                "address": "6D",
                "name": "ARROW RIGHT"
            },
            {
                "address": "6E",
                "name": "POSITION"
            },
            {
                "address": "6F",
                "name": "PIP AUDIO"
            },
            {
                "address": "71",
                "name": "INPUT: DTV ANT"
            },
            {
                "address": "72",
                "name": "INPUT 3"
            },
            {
                "address": "72",
                "name": "INPUT: VIDEO 3"
            },
            {
                "address": "76",
                "name": "PIP CHAN +"
            },
            {
                "address": "76",
                "name": "PIP CHANNEL +"
            },
            {
                "address": "77",
                "name": "PIP"
            },
            {
                "address": "77",
                "name": "PIP ON/OFF"
            },
            {
                "address": "77",
                "name": "TV PIP"
            },
            {
                "address": "77",
                "name": "PIP/POP"
            },
            {
                "address": "79",
                "name": "INPUT: DTV"
            },
            {
                "address": "7A",
                "name": "INPUT; VIDEO 4"
            },
            {
                "address": "7D",
                "name": "HOME"
            },
            {
                "address": "7D",
                "name": "TV HOME"
            },
            {
                "address": "7E",
                "name": "PIP CHAN -"
            },
            {
                "address": "7E",
                "name": "PIP CHANNEL -"
            },
            {
                "address": "7F",
                "name": "EXCH"
            }
        ],
        "device_address": "-80000000",
        "protocol": "MITSUBISHI"
    },
    "manufacturer": "Mitsubishi",
    "model": "",
    "name": "Mitsubishi TV",
    "target": "TV"
}
