{
    "display_name": "TV_1127",
    "ir": {
        "commands": [
            {
                "address": "0",
                "name": "DIGIT_1"
            },
            {
                "address": "1",
                "name": "DIGIT_4"
            },
            {
                "address": "2",
                "name": "DIGIT_7"
            },
            {
                "address": "5",
                "name": "KEY_MUTE"
            },
            {
                "address": "8",
                "name": "DIGIT_2"
            },
            {
                "address": "9",
                "name": "DIGIT_5"
            },
            {
                "address": "A",
                "name": "DIGIT_8"
            },
            {
                "address": "E",
                "name": "DIGIT_0"
            },
            {
                "address": "10",
                "name": "DIGIT_3"
            },
            {
                "address": "11",
                "name": "DIGIT_6"
            },
            {
                "address": "12",
                "name": "DIGIT_9"
            },
            {
                "address": "15",
                "name": "KEY_BLUE"
            },
            {
                "address": "1D",
                "name": "KEY_POWER"
            },
            {
                "address": "1E",
                "name": "STD_VALUES"
            },
            {
                "address": "29",
                "name": "KEY_VOLUMEUP"
            },
            {
                "address": "2A",
                "name": "KEY_VOLUMEDOWN"
            },
            {
                "address": "38",
                "name": "KEY_YELLOW"
            },
            {
                "address": "39",
                "name": "KEY_RED"
            },
            {
                "address": "3B",
                "name": "KEY_GREEN"
            },
            {
                "address": "3E",
                "name": "KEY_VIDEO"
            }
        ],
        "device_address": "-80000000",
        "protocol": "RECS80"
    },
    "manufacturer": "TELEFUNKEN",
    "model": "",
    "name": "TELEFUNKEN TV_1127",
    "target": "TV_1127"
}
