{
    "display_name": "Receiver",
    "ir": {
        "commands": [
            {
                "address": "2",
                "name": "VOLUME +"
            },
            {
                "address": "4",
                "name": "SET"
            },
            {
                "address": "6",
                "name": "CURSOR RIGHT"
            },
            {
                "address": "C",
                "name": "CURSOR UP"
            },
            {
                "address": "D",
                "name": "CURSOR DOWN"
            },
            {
                "address": "E",
                "name": "CURSOR LEFT"
            }
        ],
        "device_address": "0",
        "protocol": "NEC1"
    },
    "manufacturer": "Harman Kardon",
    "model": "",
    "name": "Harman Kardon Receiver",
    "target": "Receiver"
}
